git_refs.py
git_refs-1.1.dist-info/DESCRIPTION.rst
git_refs-1.1.dist-info/METADATA
git_refs-1.1.dist-info/RECORD
git_refs-1.1.dist-info/WHEEL
git_refs-1.1.dist-info/entry_points.txt
git_refs-1.1.dist-info/metadata.json
git_refs-1.1.dist-info/top_level.txt
