Metadata-Version: 2.0
Name: git-refs
Version: 1.1
Summary: list git references(branches, tags) on local and remote repositories
Home-page: https://github.com/weaming/git-refs
Author: weaming
Author-email: garden.yuen@gmail.com
License: UNKNOWN
Project-URL: Bug Reports, https://github.com/weaming/git-refs
Project-URL: Source, https://github.com/weaming/git-refs
Keywords: git,cli,develop
Platform: UNKNOWN
Requires-Dist: gitpython
